candor/__init__.py
candor/candor.py
candor_test-1.1.5.dist-info/METADATA
candor_test-1.1.5.dist-info/WHEEL
candor_test-1.1.5.dist-info/top_level.txt
candor_test-1.1.5.dist-info/RECORD
