Metadata-Version: 2.1
Name: candor-test
Version: 1.1.5
Summary: Simple wrapper for the Candor API.
Home-page: https://github.com/FroostySnoowman/Candor
Author: FroostySnoowman
Author-email: froostysnoowmanbusiness@gmail.com
Requires-Dist: requests
